Workbook

Sheet Eingaben
A1: fam Preis- und Umsatzmodell
A2: Alle gelb markierten Werte sind Annahmen und können geändert werden.
A4: Preise für kaufbare Abos
A5: Stufe | B5: Periode | C5: Bruttopreis (€) | D5: Vorschlag / Notiz
A6: Plus | B6: Monat | C6: 4.99 | D6: Werbefrei + Automationen
A7: Plus | B7: Jahr | C7: 39.99 | D7: ca. 3,33 €/Monat
A8: AI | B8: Monat | C8: 8.99 | D8: Plus inklusive + KI
A9: AI | B9: Jahr | C9: 69.99 | D9: ca. 5,83 €/Monat
A12: Steuern und Plattformgebühren
A13: Annahme | B13: Wert | C13: Verwendung | D13: Hinweis
A14: Umsatzsteuer / VAT | B14: 0.19 | C14: Preis enthält VAT | D14: Deutschland-Default; je Markt anpassen
A15: Apple Store-Gebühr | B15: 0.15 | C15: Gebühr auf Nettoerlös vor Store-Gebühr | D15: Default für Small Business / qualifizierende Abos
A16: Google Play-Gebühr | B16: 0.15 | C16: Gebühr auf Nettoerlös vor Store-Gebühr | D16: Default für automatisch verlängernde Abos
A17: RevenueCat-Gebühr | B17: 0 | C17: Zusätzlicher Prozentsatz nach Store-Gebühr | D17: Falls euer Vertrag eine Gebühr vorsieht
A18: Erstattungs-/Ausfallreserve | B18: 0.02 | C18: Reserve auf Nettoerlös vor Gebühren | D18: Optionaler Sicherheitsabschlag
A21: Monatliche Infra- und Betriebskosten
A22: Kostenart | B22: Wert (€) | C22: Berechnung | D22: Hinweis
A23: Fixkosten pro Monat | B23: 0 | C23: Direkt vom Gesamt-Deckungsbeitrag abgezogen | D23: z. B. Supabase-Grundpreis, Monitoring, Domains
A24: Backend/DB je zahlendem Haushalt | B24: 0 | C24: Je Plus- oder AI-Haushalt | D24: variable Datenbank-/Storage-Kosten
A25: KI-Kosten je AI-Haushalt | B25: 0 | C25: Zusätzlich je AI-Haushalt | D25: Modellkosten, APIs, Sprachdienste
A26: Support / sonstige Kosten je Haushalt | B26: 0 | C26: Je Plus- oder AI-Haushalt | D26: optional
A29: Aktive zahlende Abos pro Monat
A30: Store | B30: Stufe | C30: Periode | D30: Anzahl
A31: Apple | B31: 0 | C31: Monat
A32: Apple | B32: 0 | C32: Jahr
A33: Apple | B33: 0 | C33: Monat
A34: Apple | B34: 0 | C34: Jahr
A35: Google | B35: 0 | C35: Monat
A36: Google | B36: 0 | C36: Jahr
A37: Google | B37: 0 | C37: Monat
A38: Google | B38: 0 | C38: Jahr
A41: Hinweis: Bei Jahresabos zeigt die Auswertung eine monatliche Run-Rate. Der tatsächliche Zahlungseingang erfolgt jährlich.

Sheet Auswertung
A1: fam Auswertung: Store-Umsatz und Deckungsbeitrag
A2: Alle gelb markierten Werte sind Annahmen und können geändert werden.
A3: Die Rechnung zieht zunächst VAT ab, danach Store-/RevenueCat-Gebühren und anschließend die variablen Infra-Kosten.
A5: Store | B5: Stufe | C5: Periode | D5: Abos | E5: Preis brutto / Periode | F5: Brutto Run-Rate / Monat | G5: VAT-Anteil | H5: Netto vor Gebühren | I5: Store-Gebühr | J5: RevenueCat-Gebühr | K5: Reserve | L5: Auszahlung nach Gebühren | M5: Variable Infra | N5: Deckungsbeitrag
A6: =Eingaben!A31 | B6: =Eingaben!B31 | C6: =Eingaben!C31 | D6: =Eingaben!D31 | E6: =Eingaben!C6 | F6: =IF(C6="Jahr",D6*E6/12,D6*E6) | G6: =F6*Eingaben!$B$14/(1+Eingaben!$B$14) | H6: =F6-G6 | I6: =H6*IF(A6="Apple",Eingaben!$B$15,Eingaben!$B$16) | J6: =H6*Eingaben!$B$17 | K6: =H6*Eingaben!$B$18 | L6: =H6-I6-J6-K6 | M6: =D6*(Eingaben!$B$24+Eingaben!$B$26+IF(B6="AI",Eingaben!$B$25,0)) | N6: =L6-M6
A7: =Eingaben!A32 | B7: =Eingaben!B32 | C7: =Eingaben!C32 | D7: =Eingaben!D32 | E7: =Eingaben!C7 | F7: =IF(C7="Jahr",D7*E7/12,D7*E7) | G7: =F7*Eingaben!$B$14/(1+Eingaben!$B$14) | H7: =F7-G7 | I7: =H7*IF(A7="Apple",Eingaben!$B$15,Eingaben!$B$16) | J7: =H7*Eingaben!$B$17 | K7: =H7*Eingaben!$B$18 | L7: =H7-I7-J7-K7 | M7: =D7*(Eingaben!$B$24+Eingaben!$B$26+IF(B7="AI",Eingaben!$B$25,0)) | N7: =L7-M7
A8: =Eingaben!A33 | B8: =Eingaben!B33 | C8: =Eingaben!C33 | D8: =Eingaben!D33 | E8: =Eingaben!C8 | F8: =IF(C8="Jahr",D8*E8/12,D8*E8) | G8: =F8*Eingaben!$B$14/(1+Eingaben!$B$14) | H8: =F8-G8 | I8: =H8*IF(A8="Apple",Eingaben!$B$15,Eingaben!$B$16) | J8: =H8*Eingaben!$B$17 | K8: =H8*Eingaben!$B$18 | L8: =H8-I8-J8-K8 | M8: =D8*(Eingaben!$B$24+Eingaben!$B$26+IF(B8="AI",Eingaben!$B$25,0)) | N8: =L8-M8
A9: =Eingaben!A34 | B9: =Eingaben!B34 | C9: =Eingaben!C34 | D9: =Eingaben!D34 | E9: =Eingaben!C9 | F9: =IF(C9="Jahr",D9*E9/12,D9*E9) | G9: =F9*Eingaben!$B$14/(1+Eingaben!$B$14) | H9: =F9-G9 | I9: =H9*IF(A9="Apple",Eingaben!$B$15,Eingaben!$B$16) | J9: =H9*Eingaben!$B$17 | K9: =H9*Eingaben!$B$18 | L9: =H9-I9-J9-K9 | M9: =D9*(Eingaben!$B$24+Eingaben!$B$26+IF(B9="AI",Eingaben!$B$25,0)) | N9: =L9-M9
A10: =Eingaben!A35 | B10: =Eingaben!B35 | C10: =Eingaben!C35 | D10: =Eingaben!D35 | E10: =Eingaben!C6 | F10: =IF(C10="Jahr",D10*E10/12,D10*E10) | G10: =F10*Eingaben!$B$14/(1+Eingaben!$B$14) | H10: =F10-G10 | I10: =H10*IF(A10="Apple",Eingaben!$B$15,Eingaben!$B$16) | J10: =H10*Eingaben!$B$17 | K10: =H10*Eingaben!$B$18 | L10: =H10-I10-J10-K10 | M10: =D10*(Eingaben!$B$24+Eingaben!$B$26+IF(B10="AI",Eingaben!$B$25,0)) | N10: =L10-M10
A11: =Eingaben!A36 | B11: =Eingaben!B36 | C11: =Eingaben!C36 | D11: =Eingaben!D36 | E11: =Eingaben!C7 | F11: =IF(C11="Jahr",D11*E11/12,D11*E11) | G11: =F11*Eingaben!$B$14/(1+Eingaben!$B$14) | H11: =F11-G11 | I11: =H11*IF(A11="Apple",Eingaben!$B$15,Eingaben!$B$16) | J11: =H11*Eingaben!$B$17 | K11: =H11*Eingaben!$B$18 | L11: =H11-I11-J11-K11 | M11: =D11*(Eingaben!$B$24+Eingaben!$B$26+IF(B11="AI",Eingaben!$B$25,0)) | N11: =L11-M11
A12: =Eingaben!A37 | B12: =Eingaben!B37 | C12: =Eingaben!C37 | D12: =Eingaben!D37 | E12: =Eingaben!C8 | F12: =IF(C12="Jahr",D12*E12/12,D12*E12) | G12: =F12*Eingaben!$B$14/(1+Eingaben!$B$14) | H12: =F12-G12 | I12: =H12*IF(A12="Apple",Eingaben!$B$15,Eingaben!$B$16) | J12: =H12*Eingaben!$B$17 | K12: =H12*Eingaben!$B$18 | L12: =H12-I12-J12-K12 | M12: =D12*(Eingaben!$B$24+Eingaben!$B$26+IF(B12="AI",Eingaben!$B$25,0)) | N12: =L12-M12
A13: =Eingaben!A38 | B13: =Eingaben!B38 | C13: =Eingaben!C38 | D13: =Eingaben!D38 | E13: =Eingaben!C9 | F13: =IF(C13="Jahr",D13*E13/12,D13*E13) | G13: =F13*Eingaben!$B$14/(1+Eingaben!$B$14) | H13: =F13-G13 | I13: =H13*IF(A13="Apple",Eingaben!$B$15,Eingaben!$B$16) | J13: =H13*Eingaben!$B$17 | K13: =H13*Eingaben!$B$18 | L13: =H13-I13-J13-K13 | M13: =D13*(Eingaben!$B$24+Eingaben!$B$26+IF(B13="AI",Eingaben!$B$25,0)) | N13: =L13-M13
A16: Gesamt | D16: =SUM(D6:D13) | E16: =SUM(E6:E13) | F16: =SUM(F6:F13) | G16: =SUM(G6:G13) | H16: =SUM(H6:H13) | I16: =SUM(I6:I13) | J16: =SUM(J6:J13) | K16: =SUM(K6:K13) | ... N16: =SUM(N6:N13)
A18: Fixkosten pro Monat | B18: =Eingaben!B23
A19: Deckungsbeitrag nach Fixkosten | B19: =N16-B18
A20: Effektiver Nettoerlös je 1 € Bruttoumsatz | B20: =IF(F16=0,0,B19/F16)

Sheet Hinweise
A1: Modellannahmen und Quellen
A3: Wichtige Modelllogik
A4: 1. Free ist kein RevenueCat-Entitlement. Free bedeutet: kein aktives Plus- oder AI-Entitlement.
A5: 2. Die Preise sind Bruttopreise. Das Modell zieht die eingetragene VAT rechnerisch zuerst ab.
A6: 3. Apple und Google werden getrennt gerechnet. Die Prozentsätze sind editierbare Defaults, keine unveränderlichen Tatsachen.
A7: 4. Jahresabos werden als Monats-Run-Rate dargestellt. Für Cashflow-Planung braucht ihr zusätzlich neue Abschlüsse und Verlängerungen pro Monat.
A8: 5. Bei einem haushaltsweiten Abo ist ein Eintrag unter 'Aktive zahlende Abos' ein zahlender Haushalt bzw. eine zahlende Subscription, nicht jedes Haushaltsmitglied.
A9: 6. Der Deckungsbeitrag ist keine Steuer- oder Bilanzberatung. Rückerstattungen, lokale Preisstaffeln und Wechselkurse können zusätzliche Abweichungen erzeugen.
A12: Offizielle Gebührenreferenzen
A13: Apple App Store Small Business Program | B13: https://developer.apple.com/app-store/small-business-program/
A14: Apple Developer Program fees and qualifying subscriptions | B14: https://developer.apple.com/programs/whats-included/
A15: Google Play service fees | B15: https://support.google.com/googleplay/android-developer/answer/112622
