Workbook

Sheet Dashboard
A1: fam Monetarisierungs-Dashboard
A2: Wähle ein Szenario. Die Werte zeigen eine monatliche Run-Rate, inklusive Free-Werbeumsatz und geschätztem echtem Gewinn.
A3: Aktives Szenario | B3: Basis
A5: Bruttoumsatz / Monat | B5: =INDEX(Szenarien!$E$13:$E$15,MATCH($B$3,Szenarien!$A$13:$A$15,0))+INDEX(Szenarien!$J$13:$J$15,MATCH($B$3,Szenarien!$A$13:$A$15,0)) | C5: Echter Gewinn / Monat | D5: =INDEX(Szenarien!$O$13:$O$15,MATCH($B$3,Szenarien!$A$13:$A$15,0))
A6: Gewinnmarge | B6: =INDEX(Szenarien!$P$13:$P$15,MATCH($B$3,Szenarien!$A$13:$A$15,0)) | C6: Break-even Haushalte | D6: =INDEX(Szenarien!$S$13:$S$15,MATCH($B$3,Szenarien!$A$13:$A$15,0))
A9: Ausgewähltes Szenario: Apple vs. Google | F9: Szenarienvergleich
A10: Metrik | B10: Apple | C10: Google | D10: Gesamt | F10: Szenario | H10: Brutto / Monat | I10: Echter Gewinn | J10: Marge | K10: Break-even
A11: Free-Nutzer | B11: =INDEX(Szenarien!$B$6:$B$8,MATCH($B$3,Szenarien!$A$6:$A$8,0)) | C11: =INDEX(Szenarien!$C$6:$C$8,MATCH($B$3,Szenarien!$A$6:$A$8,0)) | D11: =SUM(B11:C11) | F11: =Szenarien!A13 | H11: =Szenarien!E13+Szenarien!J13 | I11: =Szenarien!O13 | J11: =Szenarien!P13 | K11: =Szenarien!S13
A12: Plus-Haushalte | B12: =SUMIFS(Detail!$E:$E,Detail!$A:$A,$B$3,Detail!$B:$B,"Apple",Detail!$C:$C,"Plus") | C12: =SUMIFS(Detail!$E:$E,Detail!$A:$A,$B$3,Detail!$B:$B,"Google",Detail!$C:$C,"Plus") | D12: =SUM(B12:C12) | F12: =Szenarien!A14 | H12: =Szenarien!E14+Szenarien!J14 | I12: =Szenarien!O14 | J12: =Szenarien!P14 | K12: =Szenarien!S14
A13: AI-Haushalte | B13: =SUMIFS(Detail!$E:$E,Detail!$A:$A,$B$3,Detail!$B:$B,"Apple",Detail!$C:$C,"AI") | C13: =SUMIFS(Detail!$E:$E,Detail!$A:$A,$B$3,Detail!$B:$B,"Google",Detail!$C:$C,"AI") | D13: =SUM(B13:C13) | F13: =Szenarien!A15 | H13: =Szenarien!E15+Szenarien!J15 | I13: =Szenarien!O15 | J13: =Szenarien!P15 | K13: =Szenarien!S15
A14: Bruttoumsatz Abos / Monat | B14: =SUMIFS(Detail!$G:$G,Detail!$A:$A,$B$3,Detail!$B:$B,"Apple") | C14: =SUMIFS(Detail!$G:$G,Detail!$A:$A,$B$3,Detail!$B:$B,"Google") | D14: =SUM(B14:C14)
A15: VAT | B15: =SUMIFS(Detail!$H:$H,Detail!$A:$A,$B$3,Detail!$B:$B,"Apple") | C15: =SUMIFS(Detail!$H:$H,Detail!$A:$A,$B$3,Detail!$B:$B,"Google") | D15: =SUM(B15:C15) | F15: Die Szenarien zeigen, wie empfindlich Gewinn und Break-even auf Nutzer- und Abowachstum reagieren.
A16: Store-Gebühr | B16: =SUMIFS(Detail!$J:$J,Detail!$A:$A,$B$3,Detail!$B:$B,"Apple") | C16: =SUMIFS(Detail!$J:$J,Detail!$A:$A,$B$3,Detail!$B:$B,"Google") | D16: =SUM(B16:C16)
A17: RevenueCat | B17: =SUMIFS(Detail!$K:$K,Detail!$A:$A,$B$3,Detail!$B:$B,"Apple") | C17: =SUMIFS(Detail!$K:$K,Detail!$A:$A,$B$3,Detail!$B:$B,"Google") | D17: =SUM(B17:C17)
A18: Refund-/Ausfallreserve | B18: =SUMIFS(Detail!$L:$L,Detail!$A:$A,$B$3,Detail!$B:$B,"Apple") | C18: =SUMIFS(Detail!$L:$L,Detail!$A:$A,$B$3,Detail!$B:$B,"Google") | D18: =SUM(B18:C18)
A19: Auszahlung Abos | B19: =SUMIFS(Detail!$M:$M,Detail!$A:$A,$B$3,Detail!$B:$B,"Apple") | C19: =SUMIFS(Detail!$M:$M,Detail!$A:$A,$B$3,Detail!$B:$B,"Google") | D19: =SUM(B19:C19)
A20: Free-Werbeumsatz brutto | B20: =B11*Eingaben!$B$27 | C20: =C11*Eingaben!$B$27 | D20: =SUM(B20:C20)
A21: Werbenetzwerk-Gebühr | B21: =B20*Eingaben!$B$17 | C21: =C20*Eingaben!$B$17 | D21: =SUM(B21:C21)
A22: Werbeerlös netto | B22: =B20-B21 | C22: =C20-C21 | D22: =SUM(B22:C22)
A23: Gesamtumsatz brutto | B23: =B14+B20 | C23: =C14+C20 | D23: =SUM(B23:C23)
A24: Variable Infra | B24: =SUMIFS(Detail!$N:$N,Detail!$A:$A,$B$3,Detail!$B:$B,"Apple") | C24: =SUMIFS(Detail!$N:$N,Detail!$A:$A,$B$3,Detail!$B:$B,"Google") | D24: =SUM(B24:C24)
A25: Fixkostenanteil | B25: =IF(SUM($B$11:$C$13)=0,0,Eingaben!$B$22*SUM(B11:B13)/SUM($B$11:$C$13)) | C25: =IF(SUM($B$11:$C$13)=0,0,Eingaben!$B$22*SUM(C11:C13)/SUM($B$11:$C$13)) | D25: =SUM(B25:C25)
A26: Echter Gewinn | B26: =B19+B22-B24-B25 | C26: =C19+C22-C24-C25 | D26: =SUM(B26:C26)
A27: Gewinnmarge | B27: =IFERROR(B26/B23,0) | C27: =IFERROR(C26/C23,0) | D27: =IFERROR(D26/D23,0)
A30: Break-even
A31: Fixkosten gesamt | B31: =Eingaben!$B$22
A32: Netto-Werbebeitrag Free | B32: =D22-D11*Eingaben!$B$23
A33: Ø Deckungsbeitrag je zahlendem Haushalt | B33: =IFERROR(SUMIFS(Detail!$O:$O,Detail!$A:$A,$B$3)/(D12+D13),0)
A34: Break-even bei aktuellem Plus/AI-Mix | B34: =IF(B33<=0,"n/a",MAX(0,(B31-B32)/B33))
A35: Aktuell zahlende Haushalte | B35: =D12+D13
A36: Abstand zum Break-even | B36: =IF(ISNUMBER(B34),B35-B34,"n/a")

Sheet Eingaben
A1: fam Eingaben
A2: Nur gelbe Felder ändern. Alle Berechnungen aktualisieren sich beim Öffnen in Excel automatisch.
A4: 1. Preise für zahlende Abos
A5: Stufe | B5: Preis monatlich brutto | C5: Preis jährlich brutto | D5: Was bekommt der Haushalt? | E5: Einheit
A6: Plus | B6: 4.99 | C6: 39.99 | D6: Werbefrei + Automationen | E6: Euro
A7: AI | B7: 8.99 | C7: 69.99 | D7: Plus inklusive + KI-Funktionen | E7: Euro
A10: 2. Gebühren und Steuern
A11: Annahme | B11: Wert | C11: Wird angewendet auf | D11: Startwert | E11: Hinweis
A12: VAT / Umsatzsteuer | B12: 0.19 | C12: Abo-Bruttoumsatz | D12: editierbar | E12: Deutschland-Default
A13: Apple Store-Gebühr | B13: 0.15 | C13: Netto-Aboerlös | D13: editierbar | E13: Programmabhängig
A14: Google Play-Gebühr | B14: 0.15 | C14: Netto-Aboerlös | D14: editierbar | E14: Abo-Default
A15: RevenueCat-Gebühr | B15: 0 | C15: Netto-Aboerlös | D15: editierbar | E15: Vertrag prüfen
A16: Refund-/Ausfallreserve | B16: 0.02 | C16: Netto-Aboerlös | D16: editierbar | E16: Optional
A17: Werbenetzwerk-Gebühr | B17: 0.15 | C17: Free-Werbeumsatz | D17: editierbar | E17: Optional, z. B. AdMob
A20: 3. Monatliche Betriebs- und Infra-Kosten
A21: Kosten / Erlös | B21: Wert | C21: Berechnung | D21: Beispiel | E21: Hinweis
A22: Fixkosten gesamt pro Monat | B22: 100 | C22: einmal pro Monat | D22: editierbar | E22: z. B. Supabase, Monitoring, Domains
A23: Infra je Free-Nutzer pro Monat | B23: 0.03 | C23: je aktiver Free-Nutzer | D23: editierbar | E23: variable Backend-/Storage-Kosten
A24: Infra je zahlendem Haushalt | B24: 0.1 | C24: je Plus- oder AI-Haushalt | D24: editierbar | E24: variable Datenbankkosten
A25: KI-Kosten je AI-Haushalt | B25: 0.8 | C25: zusätzlich je AI-Haushalt | D25: editierbar | E25: Modelle, APIs, Sprache
A26: Support / sonstige Kosten je Haushalt | B26: 0.05 | C26: je Plus- oder AI-Haushalt | D26: editierbar | E26: optional
A27: Free-Werbeumsatz je Nutzer | B27: 0.25 | C27: brutto je aktivem Free-Nutzer | D27: editierbar | E27: Beispielannahme, ersetzen
A31: Die gelben Beispielwerte sind bewusst nur Startwerte. Besonders Werbeumsatz, KI-Kosten und Plattformgebühren sollten mit euren echten Abrechnungen ersetzt werden.

Sheet Szenarien
A1: fam Szenarien
A2: Tragt hier Nutzerzahlen und zahlende Haushalte ein. Jahresabos werden in der Auswertung auf eine monatliche Run-Rate umgerechnet.
A4: Gelbe Felder: Szenario-Annahmen
A5: Szenario | B5: Free Apple | C5: Free Google | D5: Plus Apple Monat | E5: Plus Apple Jahr | F5: AI Apple Monat | G5: AI Apple Jahr | H5: Plus Google Monat | I5: Plus Google Jahr | J5: AI Google Monat | K5: AI Google Jahr
A6: Konservativ | B6: 600 | C6: 400 | D6: 20 | E6: 30 | F6: 2 | G6: 3 | H6: 15 | I6: 20 | J6: 1 | K6: 2
A7: Basis | B7: 3000 | C7: 2000 | D7: 90 | E7: 110 | F7: 10 | G7: 15 | H7: 70 | I7: 80 | J7: 8 | K7: 12
A8: Wachstum | B8: 15000 | C8: 10000 | D8: 450 | E8: 550 | F8: 60 | G8: 90 | H8: 350 | I8: 450 | J8: 50 | K8: 80
A11: Automatisch berechnete Szenario-Ergebnisse
A12: Szenario | B12: Free gesamt | C12: Plus gesamt | D12: AI gesamt | E12: Abo-Brutto / Monat | F12: VAT | G12: Store-Gebühr | H12: RevenueCat | I12: Reserve | J12: Werbung brutto | K12: Werbenetzwerk-Gebühr | L12: Werbung netto | M12: Variable Infra | N12: Fixkosten | O12: Echter Gewinn | P12: Gewinnmarge | Q12: Zahlende Haushalte | R12: Ø Beitrag je Abo | S12: Break-even Haushalte | T12: Apple Abo-Brutto | U12: Google Abo-Brutto | V12: Apple echter Gewinn | W12: Google echter Gewinn
A13: =A6 | B13: =B6+C6 | C13: =D6+E6+H6+I6 | D13: =F6+G6+J6+K6 | E13: =SUMIFS(Detail!$G:$G,Detail!$A:$A,$A13) | F13: =SUMIFS(Detail!$H:$H,Detail!$A:$A,$A13) | G13: =SUMIFS(Detail!$J:$J,Detail!$A:$A,$A13) | H13: =SUMIFS(Detail!$K:$K,Detail!$A:$A,$A13) | I13: =SUMIFS(Detail!$L:$L,Detail!$A:$A,$A13) | J13: =B13*Eingaben!$B$27 | K13: =J13*Eingaben!$B$17 | L13: =J13-K13 | M13: =SUMIFS(Detail!$N:$N,Detail!$A:$A,$A13)+B13*Eingaben!$B$23 | N13: =Eingaben!$B$22 | O13: =SUMIFS(Detail!$O:$O,Detail!$A:$A,$A13)+L13-M13-N13 | P13: =IFERROR(O13/(E13+J13),0) | Q13: =C13+D13 | R13: =IFERROR(SUMIFS(Detail!$O:$O,Detail!$A:$A,$A13)/Q13,0) | S13: =IF(R13<=0,"n/a",MAX(0,(N13-(L13-B13*Eingaben!$B$23))/R13)) | T13: =SUMIFS(Detail!$G:$G,Detail!$A:$A,$A13,Detail!$B:$B,"Apple") | U13: =SUMIFS(Detail!$G:$G,Detail!$A:$A,$A13,Detail!$B:$B,"Google") | V13: =SUMIFS(Detail!$O:$O,Detail!$A:$A,$A13,Detail!$B:$B,"Apple")+B6*Eingaben!$B$27*(1-Eingaben!$B$17)-B6*Eingaben!$B$23-Eingaben!$B$22*(B6+D6+E6+F6+G6)/((B6+D6+E6+F6+G6)+(C6+H6+I6+J6+K6)) | W13: =SUMIFS(Detail!$O:$O,Detail!$A:$A,$A13,Detail!$B:$B,"Google")+C6*Eingaben!$B$27*(1-Eingaben!$B$17)-C6*Eingaben!$B$23-Eingaben!$B$22*(C6+H6+I6+J6+K6)/((B6+D6+E6+F6+G6)+(C6+H6+I6+J6+K6))
A14: =A7 | B14: =B7+C7 | C14: =D7+E7+H7+I7 | D14: =F7+G7+J7+K7 | E14: =SUMIFS(Detail!$G:$G,Detail!$A:$A,$A14) | F14: =SUMIFS(Detail!$H:$H,Detail!$A:$A,$A14) | G14: =SUMIFS(Detail!$J:$J,Detail!$A:$A,$A14) | H14: =SUMIFS(Detail!$K:$K,Detail!$A:$A,$A14) | I14: =SUMIFS(Detail!$L:$L,Detail!$A:$A,$A14) | J14: =B14*Eingaben!$B$27 | K14: =J14*Eingaben!$B$17 | L14: =J14-K14 | M14: =SUMIFS(Detail!$N:$N,Detail!$A:$A,$A14)+B14*Eingaben!$B$23 | N14: =Eingaben!$B$22 | O14: =SUMIFS(Detail!$O:$O,Detail!$A:$A,$A14)+L14-M14-N14 | P14: =IFERROR(O14/(E14+J14),0) | Q14: =C14+D14 | R14: =IFERROR(SUMIFS(Detail!$O:$O,Detail!$A:$A,$A14)/Q14,0) | S14: =IF(R14<=0,"n/a",MAX(0,(N14-(L14-B14*Eingaben!$B$23))/R14)) | T14: =SUMIFS(Detail!$G:$G,Detail!$A:$A,$A14,Detail!$B:$B,"Apple") | U14: =SUMIFS(Detail!$G:$G,Detail!$A:$A,$A14,Detail!$B:$B,"Google") | V14: =SUMIFS(Detail!$O:$O,Detail!$A:$A,$A14,Detail!$B:$B,"Apple")+B7*Eingaben!$B$27*(1-Eingaben!$B$17)-B7*Eingaben!$B$23-Eingaben!$B$22*(B7+D7+E7+F7+G7)/((B7+D7+E7+F7+G7)+(C7+H7+I7+J7+K7)) | W14: =SUMIFS(Detail!$O:$O,Detail!$A:$A,$A14,Detail!$B:$B,"Google")+C7*Eingaben!$B$27*(1-Eingaben!$B$17)-C7*Eingaben!$B$23-Eingaben!$B$22*(C7+H7+I7+J7+K7)/((B7+D7+E7+F7+G7)+(C7+H7+I7+J7+K7))
A15: =A8 | B15: =B8+C8 | C15: =D8+E8+H8+I8 | D15: =F8+G8+J8+K8 | E15: =SUMIFS(Detail!$G:$G,Detail!$A:$A,$A15) | F15: =SUMIFS(Detail!$H:$H,Detail!$A:$A,$A15) | G15: =SUMIFS(Detail!$J:$J,Detail!$A:$A,$A15) | H15: =SUMIFS(Detail!$K:$K,Detail!$A:$A,$A15) | I15: =SUMIFS(Detail!$L:$L,Detail!$A:$A,$A15) | J15: =B15*Eingaben!$B$27 | K15: =J15*Eingaben!$B$17 | L15: =J15-K15 | M15: =SUMIFS(Detail!$N:$N,Detail!$A:$A,$A15)+B15*Eingaben!$B$23 | N15: =Eingaben!$B$22 | O15: =SUMIFS(Detail!$O:$O,Detail!$A:$A,$A15)+L15-M15-N15 | P15: =IFERROR(O15/(E15+J15),0) | Q15: =C15+D15 | R15: =IFERROR(SUMIFS(Detail!$O:$O,Detail!$A:$A,$A15)/Q15,0) | S15: =IF(R15<=0,"n/a",MAX(0,(N15-(L15-B15*Eingaben!$B$23))/R15)) | T15: =SUMIFS(Detail!$G:$G,Detail!$A:$A,$A15,Detail!$B:$B,"Apple") | U15: =SUMIFS(Detail!$G:$G,Detail!$A:$A,$A15,Detail!$B:$B,"Google") | V15: =SUMIFS(Detail!$O:$O,Detail!$A:$A,$A15,Detail!$B:$B,"Apple")+B8*Eingaben!$B$27*(1-Eingaben!$B$17)-B8*Eingaben!$B$23-Eingaben!$B$22*(B8+D8+E8+F8+G8)/((B8+D8+E8+F8+G8)+(C8+H8+I8+J8+K8)) | W15: =SUMIFS(Detail!$O:$O,Detail!$A:$A,$A15,Detail!$B:$B,"Google")+C8*Eingaben!$B$27*(1-Eingaben!$B$17)-C8*Eingaben!$B$23-Eingaben!$B$22*(C8+H8+I8+J8+K8)/((B8+D8+E8+F8+G8)+(C8+H8+I8+J8+K8))

Sheet Detail
A1: Detailrechnung
A2: Monatliche Run-Rate. Bei Jahresabos wird der Jahrespreis durch 12 geteilt. VAT wird vor Store-Gebühren abgezogen.
A4: Szenario | B4: Store | C4: Stufe | D4: Periode | E4: Abos | F4: Preis brutto / Periode | G4: Brutto / Monat | H4: VAT | I4: Netto vor Store-Gebühr | J4: Store-Gebühr | K4: RevenueCat | L4: Reserve | M4: Auszahlung nach Gebühren | N4: Variable Infra | O4: Beitrag vor Fixkosten
A5: =Szenarien!$A$6 | B5: Apple | C5: Plus | D5: Monat | E5: =Szenarien!$D$6 | F5: =Eingaben!$B$6 | G5: =IF(D5="Jahr",E5*F5/12,E5*F5) | H5: =G5*Eingaben!$B$12/(1+Eingaben!$B$12) | I5: =G5-H5 | J5: =I5*Eingaben!$B$13 | K5: =I5*Eingaben!$B$15 | L5: =I5*Eingaben!$B$16 | M5: =I5-J5-K5-L5 | N5: =E5*(Eingaben!$B$24+Eingaben!$B$26+IF(C5="AI",Eingaben!$B$25,0)) | O5: =M5-N5
A6: =Szenarien!$A$6 | B6: Apple | C6: Plus | D6: Jahr | E6: =Szenarien!$E$6 | F6: =Eingaben!$C$6 | G6: =IF(D6="Jahr",E6*F6/12,E6*F6) | H6: =G6*Eingaben!$B$12/(1+Eingaben!$B$12) | I6: =G6-H6 | J6: =I6*Eingaben!$B$13 | K6: =I6*Eingaben!$B$15 | L6: =I6*Eingaben!$B$16 | M6: =I6-J6-K6-L6 | N6: =E6*(Eingaben!$B$24+Eingaben!$B$26+IF(C6="AI",Eingaben!$B$25,0)) | O6: =M6-N6
A7: =Szenarien!$A$6 | B7: Apple | C7: AI | D7: Monat | E7: =Szenarien!$F$6 | F7: =Eingaben!$B$7 | G7: =IF(D7="Jahr",E7*F7/12,E7*F7) | H7: =G7*Eingaben!$B$12/(1+Eingaben!$B$12) | I7: =G7-H7 | J7: =I7*Eingaben!$B$13 | K7: =I7*Eingaben!$B$15 | L7: =I7*Eingaben!$B$16 | M7: =I7-J7-K7-L7 | N7: =E7*(Eingaben!$B$24+Eingaben!$B$26+IF(C7="AI",Eingaben!$B$25,0)) | O7: =M7-N7
A8: =Szenarien!$A$6 | B8: Apple | C8: AI | D8: Jahr | E8: =Szenarien!$G$6 | F8: =Eingaben!$C$7 | G8: =IF(D8="Jahr",E8*F8/12,E8*F8) | H8: =G8*Eingaben!$B$12/(1+Eingaben!$B$12) | I8: =G8-H8 | J8: =I8*Eingaben!$B$13 | K8: =I8*Eingaben!$B$15 | L8: =I8*Eingaben!$B$16 | M8: =I8-J8-K8-L8 | N8: =E8*(Eingaben!$B$24+Eingaben!$B$26+IF(C8="AI",Eingaben!$B$25,0)) | O8: =M8-N8
A9: =Szenarien!$A$6 | B9: Google | C9: Plus | D9: Monat | E9: =Szenarien!$H$6 | F9: =Eingaben!$B$6 | G9: =IF(D9="Jahr",E9*F9/12,E9*F9) | H9: =G9*Eingaben!$B$12/(1+Eingaben!$B$12) | I9: =G9-H9 | J9: =I9*Eingaben!$B$14 | K9: =I9*Eingaben!$B$15 | L9: =I9*Eingaben!$B$16 | M9: =I9-J9-K9-L9 | N9: =E9*(Eingaben!$B$24+Eingaben!$B$26+IF(C9="AI",Eingaben!$B$25,0)) | O9: =M9-N9
A10: =Szenarien!$A$6 | B10: Google | C10: Plus | D10: Jahr | E10: =Szenarien!$I$6 | F10: =Eingaben!$C$6 | G10: =IF(D10="Jahr",E10*F10/12,E10*F10) | H10: =G10*Eingaben!$B$12/(1+Eingaben!$B$12) | I10: =G10-H10 | J10: =I10*Eingaben!$B$14 | K10: =I10*Eingaben!$B$15 | L10: =I10*Eingaben!$B$16 | M10: =I10-J10-K10-L10 | N10: =E10*(Eingaben!$B$24+Eingaben!$B$26+IF(C10="AI",Eingaben!$B$25,0)) | O10: =M10-N10
A11: =Szenarien!$A$6 | B11: Google | C11: AI | D11: Monat | E11: =Szenarien!$J$6 | F11: =Eingaben!$B$7 | G11: =IF(D11="Jahr",E11*F11/12,E11*F11) | H11: =G11*Eingaben!$B$12/(1+Eingaben!$B$12) | I11: =G11-H11 | J11: =I11*Eingaben!$B$14 | K11: =I11*Eingaben!$B$15 | L11: =I11*Eingaben!$B$16 | M11: =I11-J11-K11-L11 | N11: =E11*(Eingaben!$B$24+Eingaben!$B$26+IF(C11="AI",Eingaben!$B$25,0)) | O11: =M11-N11
A12: =Szenarien!$A$6 | B12: Google | C12: AI | D12: Jahr | E12: =Szenarien!$K$6 | F12: =Eingaben!$C$7 | G12: =IF(D12="Jahr",E12*F12/12,E12*F12) | H12: =G12*Eingaben!$B$12/(1+Eingaben!$B$12) | I12: =G12-H12 | J12: =I12*Eingaben!$B$14 | K12: =I12*Eingaben!$B$15 | L12: =I12*Eingaben!$B$16 | M12: =I12-J12-K12-L12 | N12: =E12*(Eingaben!$B$24+Eingaben!$B$26+IF(C12="AI",Eingaben!$B$25,0)) | O12: =M12-N12
A13: =Szenarien!$A$7 | B13: Apple | C13: Plus | D13: Monat | E13: =Szenarien!$D$7 | F13: =Eingaben!$B$6 | G13: =IF(D13="Jahr",E13*F13/12,E13*F13) | H13: =G13*Eingaben!$B$12/(1+Eingaben!$B$12) | I13: =G13-H13 | J13: =I13*Eingaben!$B$13 | K13: =I13*Eingaben!$B$15 | L13: =I13*Eingaben!$B$16 | M13: =I13-J13-K13-L13 | N13: =E13*(Eingaben!$B$24+Eingaben!$B$26+IF(C13="AI",Eingaben!$B$25,0)) | O13: =M13-N13
A14: =Szenarien!$A$7 | B14: Apple | C14: Plus | D14: Jahr | E14: =Szenarien!$E$7 | F14: =Eingaben!$C$6 | G14: =IF(D14="Jahr",E14*F14/12,E14*F14) | H14: =G14*Eingaben!$B$12/(1+Eingaben!$B$12) | I14: =G14-H14 | J14: =I14*Eingaben!$B$13 | K14: =I14*Eingaben!$B$15 | L14: =I14*Eingaben!$B$16 | M14: =I14-J14-K14-L14 | N14: =E14*(Eingaben!$B$24+Eingaben!$B$26+IF(C14="AI",Eingaben!$B$25,0)) | O14: =M14-N14
A15: =Szenarien!$A$7 | B15: Apple | C15: AI | D15: Monat | E15: =Szenarien!$F$7 | F15: =Eingaben!$B$7 | G15: =IF(D15="Jahr",E15*F15/12,E15*F15) | H15: =G15*Eingaben!$B$12/(1+Eingaben!$B$12) | I15: =G15-H15 | J15: =I15*Eingaben!$B$13 | K15: =I15*Eingaben!$B$15 | L15: =I15*Eingaben!$B$16 | M15: =I15-J15-K15-L15 | N15: =E15*(Eingaben!$B$24+Eingaben!$B$26+IF(C15="AI",Eingaben!$B$25,0)) | O15: =M15-N15
A16: =Szenarien!$A$7 | B16: Apple | C16: AI | D16: Jahr | E16: =Szenarien!$G$7 | F16: =Eingaben!$C$7 | G16: =IF(D16="Jahr",E16*F16/12,E16*F16) | H16: =G16*Eingaben!$B$12/(1+Eingaben!$B$12) | I16: =G16-H16 | J16: =I16*Eingaben!$B$13 | K16: =I16*Eingaben!$B$15 | L16: =I16*Eingaben!$B$16 | M16: =I16-J16-K16-L16 | N16: =E16*(Eingaben!$B$24+Eingaben!$B$26+IF(C16="AI",Eingaben!$B$25,0)) | O16: =M16-N16
A17: =Szenarien!$A$7 | B17: Google | C17: Plus | D17: Monat | E17: =Szenarien!$H$7 | F17: =Eingaben!$B$6 | G17: =IF(D17="Jahr",E17*F17/12,E17*F17) | H17: =G17*Eingaben!$B$12/(1+Eingaben!$B$12) | I17: =G17-H17 | J17: =I17*Eingaben!$B$14 | K17: =I17*Eingaben!$B$15 | L17: =I17*Eingaben!$B$16 | M17: =I17-J17-K17-L17 | N17: =E17*(Eingaben!$B$24+Eingaben!$B$26+IF(C17="AI",Eingaben!$B$25,0)) | O17: =M17-N17
A18: =Szenarien!$A$7 | B18: Google | C18: Plus | D18: Jahr | E18: =Szenarien!$I$7 | F18: =Eingaben!$C$6 | G18: =IF(D18="Jahr",E18*F18/12,E18*F18) | H18: =G18*Eingaben!$B$12/(1+Eingaben!$B$12) | I18: =G18-H18 | J18: =I18*Eingaben!$B$14 | K18: =I18*Eingaben!$B$15 | L18: =I18*Eingaben!$B$16 | M18: =I18-J18-K18-L18 | N18: =E18*(Eingaben!$B$24+Eingaben!$B$26+IF(C18="AI",Eingaben!$B$25,0)) | O18: =M18-N18
A19: =Szenarien!$A$7 | B19: Google | C19: AI | D19: Monat | E19: =Szenarien!$J$7 | F19: =Eingaben!$B$7 | G19: =IF(D19="Jahr",E19*F19/12,E19*F19) | H19: =G19*Eingaben!$B$12/(1+Eingaben!$B$12) | I19: =G19-H19 | J19: =I19*Eingaben!$B$14 | K19: =I19*Eingaben!$B$15 | L19: =I19*Eingaben!$B$16 | M19: =I19-J19-K19-L19 | N19: =E19*(Eingaben!$B$24+Eingaben!$B$26+IF(C19="AI",Eingaben!$B$25,0)) | O19: =M19-N19
A20: =Szenarien!$A$7 | B20: Google | C20: AI | D20: Jahr | E20: =Szenarien!$K$7 | F20: =Eingaben!$C$7 | G20: =IF(D20="Jahr",E20*F20/12,E20*F20) | H20: =G20*Eingaben!$B$12/(1+Eingaben!$B$12) | I20: =G20-H20 | J20: =I20*Eingaben!$B$14 | K20: =I20*Eingaben!$B$15 | L20: =I20*Eingaben!$B$16 | M20: =I20-J20-K20-L20 | N20: =E20*(Eingaben!$B$24+Eingaben!$B$26+IF(C20="AI",Eingaben!$B$25,0)) | O20: =M20-N20
A21: =Szenarien!$A$8 | B21: Apple | C21: Plus | D21: Monat | E21: =Szenarien!$D$8 | F21: =Eingaben!$B$6 | G21: =IF(D21="Jahr",E21*F21/12,E21*F21) | H21: =G21*Eingaben!$B$12/(1+Eingaben!$B$12) | I21: =G21-H21 | J21: =I21*Eingaben!$B$13 | K21: =I21*Eingaben!$B$15 | L21: =I21*Eingaben!$B$16 | M21: =I21-J21-K21-L21 | N21: =E21*(Eingaben!$B$24+Eingaben!$B$26+IF(C21="AI",Eingaben!$B$25,0)) | O21: =M21-N21
A22: =Szenarien!$A$8 | B22: Apple | C22: Plus | D22: Jahr | E22: =Szenarien!$E$8 | F22: =Eingaben!$C$6 | G22: =IF(D22="Jahr",E22*F22/12,E22*F22) | H22: =G22*Eingaben!$B$12/(1+Eingaben!$B$12) | I22: =G22-H22 | J22: =I22*Eingaben!$B$13 | K22: =I22*Eingaben!$B$15 | L22: =I22*Eingaben!$B$16 | M22: =I22-J22-K22-L22 | N22: =E22*(Eingaben!$B$24+Eingaben!$B$26+IF(C22="AI",Eingaben!$B$25,0)) | O22: =M22-N22
A23: =Szenarien!$A$8 | B23: Apple | C23: AI | D23: Monat | E23: =Szenarien!$F$8 | F23: =Eingaben!$B$7 | G23: =IF(D23="Jahr",E23*F23/12,E23*F23) | H23: =G23*Eingaben!$B$12/(1+Eingaben!$B$12) | I23: =G23-H23 | J23: =I23*Eingaben!$B$13 | K23: =I23*Eingaben!$B$15 | L23: =I23*Eingaben!$B$16 | M23: =I23-J23-K23-L23 | N23: =E23*(Eingaben!$B$24+Eingaben!$B$26+IF(C23="AI",Eingaben!$B$25,0)) | O23: =M23-N23
A24: =Szenarien!$A$8 | B24: Apple | C24: AI | D24: Jahr | E24: =Szenarien!$G$8 | F24: =Eingaben!$C$7 | G24: =IF(D24="Jahr",E24*F24/12,E24*F24) | H24: =G24*Eingaben!$B$12/(1+Eingaben!$B$12) | I24: =G24-H24 | J24: =I24*Eingaben!$B$13 | K24: =I24*Eingaben!$B$15 | L24: =I24*Eingaben!$B$16 | M24: =I24-J24-K24-L24 | N24: =E24*(Eingaben!$B$24+Eingaben!$B$26+IF(C24="AI",Eingaben!$B$25,0)) | O24: =M24-N24
A25: =Szenarien!$A$8 | B25: Google | C25: Plus | D25: Monat | E25: =Szenarien!$H$8 | F25: =Eingaben!$B$6 | G25: =IF(D25="Jahr",E25*F25/12,E25*F25) | H25: =G25*Eingaben!$B$12/(1+Eingaben!$B$12) | I25: =G25-H25 | J25: =I25*Eingaben!$B$14 | K25: =I25*Eingaben!$B$15 | L25: =I25*Eingaben!$B$16 | M25: =I25-J25-K25-L25 | N25: =E25*(Eingaben!$B$24+Eingaben!$B$26+IF(C25="AI",Eingaben!$B$25,0)) | O25: =M25-N25
A26: =Szenarien!$A$8 | B26: Google | C26: Plus | D26: Jahr | E26: =Szenarien!$I$8 | F26: =Eingaben!$C$6 | G26: =IF(D26="Jahr",E26*F26/12,E26*F26) | H26: =G26*Eingaben!$B$12/(1+Eingaben!$B$12) | I26: =G26-H26 | J26: =I26*Eingaben!$B$14 | K26: =I26*Eingaben!$B$15 | L26: =I26*Eingaben!$B$16 | M26: =I26-J26-K26-L26 | N26: =E26*(Eingaben!$B$24+Eingaben!$B$26+IF(C26="AI",Eingaben!$B$25,0)) | O26: =M26-N26
A27: =Szenarien!$A$8 | B27: Google | C27: AI | D27: Monat | E27: =Szenarien!$J$8 | F27: =Eingaben!$B$7 | G27: =IF(D27="Jahr",E27*F27/12,E27*F27) | H27: =G27*Eingaben!$B$12/(1+Eingaben!$B$12) | I27: =G27-H27 | J27: =I27*Eingaben!$B$14 | K27: =I27*Eingaben!$B$15 | L27: =I27*Eingaben!$B$16 | M27: =I27-J27-K27-L27 | N27: =E27*(Eingaben!$B$24+Eingaben!$B$26+IF(C27="AI",Eingaben!$B$25,0)) | O27: =M27-N27
A28: =Szenarien!$A$8 | B28: Google | C28: AI | D28: Jahr | E28: =Szenarien!$K$8 | F28: =Eingaben!$C$7 | G28: =IF(D28="Jahr",E28*F28/12,E28*F28) | H28: =G28*Eingaben!$B$12/(1+Eingaben!$B$12) | I28: =G28-H28 | J28: =I28*Eingaben!$B$14 | K28: =I28*Eingaben!$B$15 | L28: =I28*Eingaben!$B$16 | M28: =I28-J28-K28-L28 | N28: =E28*(Eingaben!$B$24+Eingaben!$B$26+IF(C28="AI",Eingaben!$B$25,0)) | O28: =M28-N28

Sheet Hinweise
A1: Hinweise und Quellen
A3: Lesart des Modells
A4: 1. Free hat kein RevenueCat-Entitlement. Free-Werbeumsatz wird separat gerechnet.
A5: 2. Abo-Preise sind Bruttopreise. Das Modell zieht VAT zuerst ab und berechnet Store-Gebühren auf dem Netto-Aboerlös.
A6: 3. Jahresabos werden für die Wirtschaftlichkeit als Preis / 12 dargestellt. Tatsächlicher Cashflow entsteht bei Abschluss oder Verlängerung.
A7: 4. Fixkosten werden im Dashboard proportional auf Apple und Google verteilt, basierend auf Free-Nutzern plus zahlenden Haushalten.
A8: 5. Der echte Gewinn ist ein Modellwert: Nettoauszahlung aus Abos + Netto-Werbung - variable Infra - Fixkosten.
A9: 6. Für eine echte Store-Abrechnung müssen VAT, Store-Programm, Erstattungen, lokale Preisstaffeln und RevenueCat-Vertrag geprüft werden.
A12: Offizielle Gebührenreferenzen
A13: Apple Small Business Program | B13: https://developer.apple.com/app-store/small-business-program/
A14: Apple Developer fees and qualifying subscriptions | B14: https://developer.apple.com/programs/whats-included/
A15: Google Play service fees | B15: https://support.google.com/googleplay/android-developer/answer/112622
